<?xml version="1.0" encoding="UTF-8"?>
<scenario compiled="true" name="maze.xml" version="1.0" xmlns="nmfPlan" xmlns:CORE="coreSpecific">
  <network id="wlan5" name="wlan5">
    <point lat="47.5760421033" lon="-122.124933809" type="gps"/>
    <type>wireless</type>
    <alias domain="COREID">5</alias>
    <member type="channel">wlan5/wireless</member>
    <channel id="wlan5/wireless" name="wireless">
      <type domain="CORE">basic_range</type>
      <parameter name="range">1500.0</parameter>
      <parameter name="bandwidth">54000000</parameter>
      <parameter name="jitter">0.0</parameter>
      <parameter name="delay">20000</parameter>
      <parameter name="error">0.0</parameter>
    </channel>
  </network>
  <router id="n1" name="n1">
    <type domain="CORE">mdr</type>
    <alias domain="COREID">1</alias>
    <point lat="47.5787913618" lon="-122.1314904" type="gps"/>
    <CORE:presentation icon="/home/zhiwei/Micromouse/icons/robotblu.png"/>
  </router>
  <router id="n2" name="n2">
    <type domain="CORE">mdr</type>
    <alias domain="COREID">2</alias>
    <point lat="47.5786398849" lon="-122.109970328" type="gps"/>
    <CORE:presentation icon="/home/zhiwei/Micromouse/icons/robotgre.png"/>
  </router>
  <router id="n3" name="n3">
    <type domain="CORE">mdr</type>
    <alias domain="COREID">3</alias>
    <point lat="47.5692910308" lon="-122.131707313" type="gps"/>
    <CORE:presentation icon="/home/zhiwei/Micromouse/icons/robotpur.png"/>
  </router>
  <router id="n4" name="n4">
    <type domain="CORE">mdr</type>
    <alias domain="COREID">4</alias>
    <point lat="47.5691120101" lon="-122.110111827" type="gps"/>
    <CORE:presentation icon="/home/zhiwei/Micromouse/icons/robotyel.png"/>
  </router>
  <CORE:defaultservices>
    <device type="mdr">
      <service name="zebra"/>
      <service name="OSPFv3MDR"/>
      <service name="vtysh"/>
      <service name="IPForward"/>
      <service name="MyService"/>
    </device>
  </CORE:defaultservices>
  <CORE:sessionconfig>
    <origin alt="2.0" lat="47.5791667" lon="-122.132322" scale100="150.0"/>
    <options>
      <parameter name="controlnet">10.0.0.255/24</parameter>
    </options>
    <metadata>
      <parameter name="global_options">interface_names=no ip_addresses=yes ipv6_addresses=yes node_labels=yes link_labels=yes show_api=no background_images=no annotations=yes grid=no traffic_start=0</parameter>
      <parameter name="canvas c1">{name {Canvas1}} {wallpaper-style {scaled}} {wallpaper {/home/zhiwei/Micromouse/mazes/2012japan-ef.png}} {size {1158 772}}</parameter>
    </metadata>
  </CORE:sessionconfig>
</scenario>
